{
  "provider": {
    "name": "am_role_assignment_service_search_query"
  },
  "consumer": {
    "name": "am_org_role_mapping"
  },
  "interactions": [
    {
      "description": "RAS takes s2s/auth token and returns search query results",
      "request": {
        "method": "POST",
        "path": "/am/role-assignments/query",
        "headers": {
          "Content-Type": "application/json"
        },
        "body": {
          "roleType": [
            "ORGANISATION"
          ],
          "roleName": [
            "tribunal-caseworker",
            "senior-tribunal-caseworker"
          ],
          "roleCategory": [
            "STAFF"
          ],
          "classification": [
            "PUBLIC",
            "PRIVATE"
          ],
          "grantType": [
            "STANDARD"
          ],
          "validAt": "2021-12-04T00:00:00Z",
          "attributes": {
            "primaryLocation": [
              "219ASA"
            ],
            "jurisdiction": [
              "IA"
            ]
          }
        }
      },
      "response": {
        "status": 200,
        "headers": {
          "Content-Type": "application/vnd.uk.gov.hmcts.role-assignment-service.post-assignment-query-request+json;charset=UTF-8;version=1.0"
        },
        "body": {
          "roleAssignmentResponse": [
            {
              "actorId": "ca93ea54-c219-4c6d-add6-e687a0f1f5f7",
              "roleName": "senior-tribunal-caseworker",
              "roleCategory": "STAFF",
              "readOnly": false,
              "attributes": {
                "primaryLocation": "219ASA",
                "jurisdiction": "IA"
              },
              "id": "da3c7ad9-0be1-4f72-8224-b73e3c61d22e",
              "roleType": "ORGANISATION",
              "classification": "PRIVATE",
              "grantType": "STANDARD",
              "actorIdType": "IDAM"
            }
          ]
        },
        "matchingRules": {
          "body": {
            "$.roleAssignmentResponse": {
              "matchers": [
                {
                  "match": "type",
                  "min": 1
                }
              ],
              "combine": "AND"
            },
            "$.roleAssignmentResponse[*].id": {
              "matchers": [
                {
                  "match": "type"
                }
              ],
              "combine": "AND"
            },
            "$.roleAssignmentResponse[*].attributes.jurisdiction": {
              "matchers": [
                {
                  "match": "type"
                }
              ],
              "combine": "AND"
            },
            "$.roleAssignmentResponse[*].attributes.primaryLocation": {
              "matchers": [
                {
                  "match": "type"
                }
              ],
              "combine": "AND"
            }
          }
        }
      },
      "providerStates": [
        {
          "name": "A list of multiple role assignments for the search query"
        }
      ]
    },
    {
      "description": "RAS takes s2s/auth token and returns search query results",
      "request": {
        "method": "POST",
        "path": "/am/role-assignments/query",
        "headers": {
          "Content-Type": "application/json"
        },
        "body": {
          "attributes": {
            "primaryLocation": [
              "500A2S"
            ],
            "jurisdiction": [
              "IA"
            ]
          }
        }
      },
      "response": {
        "status": 200,
        "headers": {
          "Content-Type": "application/vnd.uk.gov.hmcts.role-assignment-service.post-assignment-query-request+json;charset=UTF-8;version=1.0"
        },
        "body": {
          "roleAssignmentResponse": [
            {
              "actorId": "234873",
              "roleName": "senior-tribunal-caseworker",
              "roleCategory": "STAFF",
              "readOnly": false,
              "attributes": {
                "primaryLocation": "500A2S",
                "jurisdiction": "IA"
              },
              "id": "14a21569-eb80-4681-b62c-6ae2ed069e6f",
              "roleType": "ORGANISATION",
              "classification": "PRIVATE",
              "grantType": "STANDARD",
              "actorIdType": "IDAM"
            }
          ]
        },
        "matchingRules": {
          "body": {
            "$.roleAssignmentResponse": {
              "matchers": [
                {
                  "match": "type",
                  "min": 1
                }
              ],
              "combine": "AND"
            },
            "$.roleAssignmentResponse[*].id": {
              "matchers": [
                {
                  "match": "type"
                }
              ],
              "combine": "AND"
            },
            "$.roleAssignmentResponse[*].attributes.jurisdiction": {
              "matchers": [
                {
                  "match": "type"
                }
              ],
              "combine": "AND"
            },
            "$.roleAssignmentResponse[*].attributes.primaryLocation": {
              "matchers": [
                {
                  "match": "type"
                }
              ],
              "combine": "AND"
            }
          }
        }
      },
      "providerStates": [
        {
          "name": "A list of role assignments for the search query by attributes"
        }
      ]
    },
    {
      "description": "RAS takes s2s/auth token and returns search query results",
      "request": {
        "method": "POST",
        "path": "/am/role-assignments/query",
        "headers": {
          "Content-Type": "application/json"
        },
        "body": {
          "roleName": [
            "senior-tribunal-caseworker"
          ]
        }
      },
      "response": {
        "status": 200,
        "headers": {
          "Content-Type": "application/vnd.uk.gov.hmcts.role-assignment-service.post-assignment-query-request+json;charset=UTF-8;version=1.0"
        },
        "body": {
          "roleAssignmentResponse": [
            {
              "actorId": "234873",
              "roleName": "senior-tribunal-caseworker",
              "roleCategory": "STAFF",
              "readOnly": false,
              "attributes": {
                "primaryLocation": "500A2S",
                "jurisdiction": "IA"
              },
              "id": "14a21569-eb80-4681-b62c-6ae2ed069e6f",
              "roleType": "ORGANISATION",
              "classification": "PRIVATE",
              "grantType": "STANDARD",
              "actorIdType": "IDAM"
            }
          ]
        },
        "matchingRules": {
          "body": {
            "$.roleAssignmentResponse": {
              "matchers": [
                {
                  "match": "type",
                  "min": 1
                }
              ],
              "combine": "AND"
            },
            "$.roleAssignmentResponse[*].id": {
              "matchers": [
                {
                  "match": "type"
                }
              ],
              "combine": "AND"
            },
            "$.roleAssignmentResponse[*].attributes.jurisdiction": {
              "matchers": [
                {
                  "match": "type"
                }
              ],
              "combine": "AND"
            },
            "$.roleAssignmentResponse[*].attributes.primaryLocation": {
              "matchers": [
                {
                  "match": "type"
                }
              ],
              "combine": "AND"
            }
          }
        }
      },
      "providerStates": [
        {
          "name": "A list of role assignments for the search query by role name"
        }
      ]
    },
    {
      "description": "RAS takes s2s/auth token and returns search query results",
      "request": {
        "method": "POST",
        "path": "/am/role-assignments/query",
        "headers": {
          "Content-Type": "application/json"
        },
        "body": {
          "actorId": [
            234873
          ]
        }
      },
      "response": {
        "status": 200,
        "headers": {
          "Content-Type": "application/vnd.uk.gov.hmcts.role-assignment-service.post-assignment-query-request+json;charset=UTF-8;version=1.0"
        },
        "body": {
          "roleAssignmentResponse": [
            {
              "actorId": "234873",
              "roleName": "senior-tribunal-caseworker",
              "roleCategory": "STAFF",
              "readOnly": false,
              "attributes": {
                "primaryLocation": "500A2S",
                "jurisdiction": "IA"
              },
              "id": "14a21569-eb80-4681-b62c-6ae2ed069e6f",
              "roleType": "ORGANISATION",
              "classification": "PRIVATE",
              "grantType": "STANDARD",
              "actorIdType": "IDAM"
            }
          ]
        },
        "matchingRules": {
          "body": {
            "$.roleAssignmentResponse": {
              "matchers": [
                {
                  "match": "type",
                  "min": 1
                }
              ],
              "combine": "AND"
            },
            "$.roleAssignmentResponse[*].id": {
              "matchers": [
                {
                  "match": "type"
                }
              ],
              "combine": "AND"
            },
            "$.roleAssignmentResponse[*].attributes.jurisdiction": {
              "matchers": [
                {
                  "match": "type"
                }
              ],
              "combine": "AND"
            },
            "$.roleAssignmentResponse[*].attributes.primaryLocation": {
              "matchers": [
                {
                  "match": "type"
                }
              ],
              "combine": "AND"
            }
          }
        }
      },
      "providerStates": [
        {
          "name": "A list of role assignments for the search query"
        }
      ]
    },
    {
      "description": "RAS takes s2s/auth token and returns search query results",
      "request": {
        "method": "POST",
        "path": "/am/role-assignments/query",
        "headers": {
          "Content-Type": "application/json"
        },
        "body": {
          "actorId": [
            234873
          ]
        }
      },
      "response": {
        "status": 200,
        "headers": {
          "Content-Type": "application/vnd.uk.gov.hmcts.role-assignment-service.post-assignment-query-request+json;charset=UTF-8;version=1.0"
        },
        "body": {
          "roleAssignmentResponse": [

          ]
        },
        "matchingRules": {
          "body": {
            "$.roleAssignmentResponse": {
              "matchers": [
                {
                  "match": "type",
                  "min": 0
                }
              ],
              "combine": "AND"
            }
          }
        }
      },
      "providerStates": [
        {
          "name": "An empty list of role assignments for the search query"
        }
      ]
    }
  ],
  "metadata": {
    "pactSpecification": {
      "version": "3.0.0"
    },
    "pact-jvm": {
      "version": "4.1.7"
    }
  }
}
