{
  "_guid_": "S-062",
  "title": "must successfully create org role mapping for Hearing Centre Team Leader and Hearing Centre Administrator",
  "_extends_": "F-007_Test_Data_Base",
  "specs": [
    "contains the actorId of the user just published who has Hearing Centre Team Leader role",
    "contains the actorId of the user just published who has Hearing Centre Administrator role"
  ],
  "method": "POST",
  "uri": "{{ROLE_ASSIGNMENT_URL}}/am/role-assignments/query",
  "request": {
    "headers": {
      "sort": "roleName",
      "direction": "ASC"
    },
    "body": {
      "actorId": "${[scenarioContext][childContexts][S-062_DeleteDataForRoleAssignments][testData][request][body][userIds]}"
    }
  },
  "expectedResponse": {
    "_extends_": "Common_200_Response",
    "body": {
      "roleAssignmentResponse": [
        {
          "id": "[[ANYTHING_PRESENT]]",
          "actorIdType": "IDAM",
          "actorId": "${[scenarioContext][testData][request][body][actorId][0]}",
          "roleType": "ORGANISATION",
          "roleName": "hearing-centre-admin",
          "classification": "PUBLIC",
          "grantType": "STANDARD",
          "roleCategory": "ADMIN",
          "readOnly": false,
          "created": "[[ANYTHING_PRESENT]]",
          "attributes": {
            "substantive": "Y",
            "primaryLocation": "[[ANYTHING_PRESENT]]",
            "jurisdiction": "CIVIL",
            "region": "2",
            "workTypes": "hearing_work"
          }
        },
        {
          "id": "[[ANYTHING_PRESENT]]",
          "actorIdType": "IDAM",
          "actorId": "${[scenarioContext][testData][request][body][actorId][0]}",
          "roleType": "ORGANISATION",
          "roleName": "hearing-centre-team-leader",
          "classification": "PUBLIC",
          "grantType": "STANDARD",
          "roleCategory": "ADMIN",
          "readOnly": false,
          "created": "[[ANYTHING_PRESENT]]",
          "attributes": {
            "substantive": "Y",
            "primaryLocation": "[[ANYTHING_PRESENT]]",
            "jurisdiction": "CIVIL",
            "region": "2",
            "workTypes": "hearing_work,access_requests"
          }
        },
        {
          "id": "[[ANYTHING_PRESENT]]",
          "actorIdType": "IDAM",
          "actorId": "${[scenarioContext][testData][request][body][actorId][0]}",
          "roleType": "ORGANISATION",
          "roleName": "hmcts-admin",
          "classification": "PRIVATE",
          "grantType": "BASIC",
          "roleCategory": "ADMIN",
          "readOnly": true,
          "created": "[[ANYTHING_PRESENT]]",
          "attributes": {
            "substantive": "N"
          }
        }
      ]
    }
  }
}
